api_homebank/__init__.py
api_homebank-0.1.dist-info/METADATA
api_homebank-0.1.dist-info/WHEEL
api_homebank-0.1.dist-info/top_level.txt
api_homebank-0.1.dist-info/RECORD
