Metadata-Version: 2.1
Name: api-homebank
Version: 0.1
Summary: Api for homebank.kz
Home-page: https://github.com/Asetss/api-homebank.kz.git
Author: Asetss
Author-email: asets@protonmail.com
License: MIT
Platform: UNKNOWN
